Hdl/Encoder/counter_delay.v
module counter_delay ( input wire clk, input wire clr, output reg out);

reg [2:0] counter=0;



always @(posedge clk) begin
    if(clr) begin
        out <= 0;
        counter<=0;
    end
    else
    begin
        if(counter<7) counter <= counter+1;
        out <= (counter==4) ? 1:0;
    end
    
end

    
endmodule

Tests/Encoder/counter_delay_tb.v
`timescale 1ms/1ps
module counter_delay_tb ();

reg clk;
reg clr=0;
wire out;

counter_delay DUT(clk,clr,out);

always #5 clk = ~clk;

always #200 clr = ~clr;

initial begin
    $dumpfile("counter_delay.vcd");
    $dumpvars;
    clk = 0;
    clr =0;
    #1000 $finish;
end

always @(posedge clk) begin
    $display("clk = %d | clr = %d | out = %d", clk, clr, out);
end

endmodule

wave/counter_delay.vcd
$date
	Thu Apr 29 22:31:39 2021
$end
$version
	Icarus Verilog
$end
$timescale
	1ps
$end
$scope module counter_delay_tb $end
$var wire 1 ! out $end
$var reg 1 " clk $end
$var reg 1 # clr $end
$scope module DUT $end
$var wire 1 " clk $end
$var wire 1 # clr $end
$var reg 3 $ counter [2:0] $end
$var reg 1 ! out $end
$upscope $end
$upscope $end
$enddefinitions $end
#0
$dumpvars
b0 $
0#
0"
x!
$end
#5000000000
0!
b1 $
1"
#10000000000
0"
#15000000000
b10 $
1"
#20000000000
0"
#25000000000
b11 $
1"
#30000000000
0"
#35000000000
b100 $
1"
#40000000000
0"
#45000000000
1!
b101 $
1"
#50000000000
0"
#55000000000
b110 $
1"
#60000000000
0"
#65000000000
b111 $
1"
#70000000000
0"
#75000000000
1"
#80000000000
0"
#85000000000
1"
#90000000000
0"
#95000000000
1"
#100000000000
0"
#105000000000
1"
#110000000000
0"
#115000000000
1"
#120000000000
0"
#125000000000
1"
#130000000000
0"
#135000000000
1"
#140000000000
0"
#145000000000
1"
#150000000000
0"
#155000000000
1"
#160000000000
0"
#165000000000
1"
#170000000000
0"
#175000000000
1"
#180000000000
0"
#185000000000
1"
#190000000000
0"
#195000000000
1"
#200000000000
0"
1#
#205000000000
b0 $
0!
1"
#210000000000
0"
#215000000000
1"
#220000000000
0"
#225000000000
1"
#230000000000
0"
#235000000000
1"
#240000000000
0"
#245000000000
1"
#250000000000
0"
#255000000000
1"
#260000000000
0"
#265000000000
1"
#270000000000
0"
#275000000000
1"
#280000000000
0"
#285000000000
1"
#290000000000
0"
#295000000000
1"
#300000000000
0"
#305000000000
1"
#310000000000
0"
#315000000000
1"
#320000000000
0"
#325000000000
1"
#330000000000
0"
#335000000000
1"
#340000000000
0"
#345000000000
1"
#350000000000
0"
#355000000000
1"
#360000000000
0"
#365000000000
1"
#370000000000
0"
#375000000000
1"
#380000000000
0"
#385000000000
1"
#390000000000
0"
#395000000000
1"
#400000000000
0"
0#
#405000000000
b1 $
1"
#410000000000
0"
#415000000000
b10 $
1"
#420000000000
0"
#425000000000
b11 $
1"
#430000000000
0"
#435000000000
b100 $
1"
#440000000000
0"
#445000000000
1!
b101 $
1"
#450000000000
0"
#455000000000
b110 $
1"
#460000000000
0"
#465000000000
b111 $
1"
#470000000000
0"
#475000000000
1"
#480000000000
0"
#485000000000
1"
#490000000000
0"
#495000000000
1"
#500000000000
0"
#505000000000
1"
#510000000000
0"
#515000000000
1"
#520000000000
0"
#525000000000
1"
#530000000000
0"
#535000000000
1"
#540000000000
0"
#545000000000
1"
#550000000000
0"
#555000000000
1"
#560000000000
0"
#565000000000
1"
#570000000000
0"
#575000000000
1"
#580000000000
0"
#585000000000
1"
#590000000000
0"
#595000000000
1"
#600000000000
0"
1#
#605000000000
b0 $
0!
1"
#610000000000
0"
#615000000000
1"
#620000000000
0"
#625000000000
1"
#630000000000
0"
#635000000000
1"
#640000000000
0"
#645000000000
1"
#650000000000
0"
#655000000000
1"
#660000000000
0"
#665000000000
1"
#670000000000
0"
#675000000000
1"
#680000000000
0"
#685000000000
1"
#690000000000
0"
#695000000000
1"
#700000000000
0"
#705000000000
1"
#710000000000
0"
#715000000000
1"
#720000000000
0"
#725000000000
1"
#730000000000
0"
#735000000000
1"
#740000000000
0"
#745000000000
1"
#750000000000
0"
#755000000000
1"
#760000000000
0"
#765000000000
1"
#770000000000
0"
#775000000000
1"
#780000000000
0"
#785000000000
1"
#790000000000
0"
#795000000000
1"
#800000000000
0"
0#
#805000000000
b1 $
1"
#810000000000
0"
#815000000000
b10 $
1"
#820000000000
0"
#825000000000
b11 $
1"
#830000000000
0"
#835000000000
b100 $
1"
#840000000000
0"
#845000000000
1!
b101 $
1"
#850000000000
0"
#855000000000
b110 $
1"
#860000000000
0"
#865000000000
b111 $
1"
#870000000000
0"
#875000000000
1"
#880000000000
0"
#885000000000
1"
#890000000000
0"
#895000000000
1"
#900000000000
0"
#905000000000
1"
#910000000000
0"
#915000000000
1"
#920000000000
0"
#925000000000
1"
#930000000000
0"
#935000000000
1"
#940000000000
0"
#945000000000
1"
#950000000000
0"
#955000000000
1"
#960000000000
0"
#965000000000
1"
#970000000000
0"
#975000000000
1"
#980000000000
0"
#985000000000
1"
#990000000000
0"
#995000000000
1"
#1000000000000
0"
1#
