Hdl/Encoder/prio_enco_9x4.v
module prio_enco_9x4 (
  output wire [3:0] d_out,
  input wire[9:0] d_in,
  input wire enable,
  output wire loadn
);
// Usamos do seguinte mapeamento:
/*
IDLE -> 0000000000 (SEM ENTRADAS NO TECLADO) 
0    -> 0000000001
1    -> 0000000010
2    -> 0000000100
3    -> 0000001000
4    -> 0000010000
5    -> 0000100000
6    -> 0001000000
7    -> 0010000000
8    -> 0100000000
9    -> 1000000000
*/

      assign loadn = (enable | ~(d_in[0] | d_in[1] | d_in[2] | d_in[3] | d_in[4] | d_in[5] | d_in[6] | d_in[7] | d_in[8] | d_in[9]));
      assign d_out = (d_in[9] ==1'b1) ? 4'b1001:
                      (d_in[8] ==1'b1) ? 4'b1000:
                      (d_in[7] ==1'b1) ? 4'b0111:
                      (d_in[6] ==1'b1) ? 4'b0110:
                      (d_in[5] ==1'b1) ? 4'b0101:
                      (d_in[4] ==1'b1) ? 4'b0100:
                      (d_in[3] ==1'b1) ? 4'b0011:
                      (d_in[2] ==1'b1) ? 4'b0010:
                      (d_in[1] ==1'b1) ? 4'b0001:
                      (d_in[0] ==1'b1) ? 4'b0000: 4'b0000;
endmodule

Tests/Encoder/tb_encoder.v
`timescale 1ps/1ps

module tb_encoder(); 

reg  [9:0] y; 
wire [3:0] a;
reg enable;
wire loadn;
integer i;
 
prio_enco_9x4 U(.d_out(a), .d_in(y),.loadn(loadn), .enable(enable));

initial
    begin 
    $dumpfile("encoderWave.vcd");
	  $dumpvars(0,tb_encoder);
    //Carregando 3 no codificador
    enable = 1;
    i = 0;
    for(i=0;i<10;i = i+1)
    begin
      y = (1<<i);
      #10 enable = 0;
      #10 enable = 1;
    end
    end

    
    
endmodule

wave/encoderWave.vcd
$date
	Thu Apr 29 16:53:52 2021
$end
$version
	Icarus Verilog
$end
$timescale
	1ps
$end
$scope module tb_encoder $end
$var wire 1 ! loadn $end
$var wire 4 " a [3:0] $end
$var reg 1 # enable $end
$var reg 10 $ y [9:0] $end
$var integer 32 % i [31:0] $end
$scope module U $end
$var wire 10 & d_in [9:0] $end
$var wire 1 # enable $end
$var wire 1 ! loadn $end
$var wire 4 ' d_out [3:0] $end
$upscope $end
$upscope $end
$enddefinitions $end
#0
$dumpvars
b0 '
b1 &
b0 %
b1 $
1#
b0 "
1!
$end
#10
0!
0#
#20
b1 "
b1 '
b10 $
b10 &
b1 %
1!
1#
#30
0!
0#
#40
b10 "
b10 '
b100 $
b100 &
b10 %
1!
1#
#50
0!
0#
#60
b11 "
b11 '
b1000 $
b1000 &
b11 %
1!
1#
#70
0!
0#
#80
b100 "
b100 '
b10000 $
b10000 &
b100 %
1!
1#
#90
0!
0#
#100
b101 "
b101 '
b100000 $
b100000 &
b101 %
1!
1#
#110
0!
0#
#120
b110 "
b110 '
b1000000 $
b1000000 &
b110 %
1!
1#
#130
0!
0#
#140
b111 "
b111 '
b10000000 $
b10000000 &
b111 %
1!
1#
#150
0!
0#
#160
b1000 "
b1000 '
b100000000 $
b100000000 &
b1000 %
1!
1#
#170
0!
0#
#180
b1001 "
b1001 '
b1000000000 $
b1000000000 &
b1001 %
1!
1#
#190
0!
0#
#200
b1010 %
1!
1#
