Hdl/Encoder/freq_converter.v
module freq_converter(input wire clk, output reg new_clk);

reg [7:0] cont;

initial begin
    cont = 0;
    new_clk = 0; 
end

always @(posedge clk)
begin
    if(cont==49)
    begin
        cont <= 0;
        new_clk <= ~new_clk;
    end
    else
    begin
        cont <= cont+1;
    end

end

endmodule

Tests/Encoder/freq_converter_tb.v
`timescale 1ms/1ps
module freq_converter_tb ();

reg clk;
wire new_clk;

freq_converter DUT (clk,new_clk);

always #5 clk  = ~clk; // A cada 10ms o clock executa um período.

initial begin
    $dumpfile("freq_converter.vcd");
    $dumpvars;
    clk=0;
    #2000 $finish;
end

always @(clk) begin
    $display("time = %d || clk = %d, new_clk = %d", $time,clk ,new_clk);
end

    
endmodule

wave/freq_converter.vcd
$date
	Sun Apr 25 18:42:35 2021
$end
$version
	Icarus Verilog
$end
$timescale
	1ps
$end
$scope module freq_converter_tb $end
$var wire 1 ! new_clk $end
$var reg 1 " clk $end
$scope module DUT $end
$var wire 1 " clk $end
$var reg 8 # cont [7:0] $end
$var reg 1 ! new_clk $end
$upscope $end
$upscope $end
$enddefinitions $end
#0
$dumpvars
b0 #
0"
0!
$end
#5000000000
b1 #
1"
#10000000000
0"
#15000000000
b10 #
1"
#20000000000
0"
#25000000000
b11 #
1"
#30000000000
0"
#35000000000
b100 #
1"
#40000000000
0"
#45000000000
b101 #
1"
#50000000000
0"
#55000000000
b110 #
1"
#60000000000
0"
#65000000000
b111 #
1"
#70000000000
0"
#75000000000
b1000 #
1"
#80000000000
0"
#85000000000
b1001 #
1"
#90000000000
0"
#95000000000
b1010 #
1"
#100000000000
0"
#105000000000
b1011 #
1"
#110000000000
0"
#115000000000
b1100 #
1"
#120000000000
0"
#125000000000
b1101 #
1"
#130000000000
0"
#135000000000
b1110 #
1"
#140000000000
0"
#145000000000
b1111 #
1"
#150000000000
0"
#155000000000
b10000 #
1"
#160000000000
0"
#165000000000
b10001 #
1"
#170000000000
0"
#175000000000
b10010 #
1"
#180000000000
0"
#185000000000
b10011 #
1"
#190000000000
0"
#195000000000
b10100 #
1"
#200000000000
0"
#205000000000
b10101 #
1"
#210000000000
0"
#215000000000
b10110 #
1"
#220000000000
0"
#225000000000
b10111 #
1"
#230000000000
0"
#235000000000
b11000 #
1"
#240000000000
0"
#245000000000
b11001 #
1"
#250000000000
0"
#255000000000
b11010 #
1"
#260000000000
0"
#265000000000
b11011 #
1"
#270000000000
0"
#275000000000
b11100 #
1"
#280000000000
0"
#285000000000
b11101 #
1"
#290000000000
0"
#295000000000
b11110 #
1"
#300000000000
0"
#305000000000
b11111 #
1"
#310000000000
0"
#315000000000
b100000 #
1"
#320000000000
0"
#325000000000
b100001 #
1"
#330000000000
0"
#335000000000
b100010 #
1"
#340000000000
0"
#345000000000
b100011 #
1"
#350000000000
0"
#355000000000
b100100 #
1"
#360000000000
0"
#365000000000
b100101 #
1"
#370000000000
0"
#375000000000
b100110 #
1"
#380000000000
0"
#385000000000
b100111 #
1"
#390000000000
0"
#395000000000
b101000 #
1"
#400000000000
0"
#405000000000
b101001 #
1"
#410000000000
0"
#415000000000
b101010 #
1"
#420000000000
0"
#425000000000
b101011 #
1"
#430000000000
0"
#435000000000
b101100 #
1"
#440000000000
0"
#445000000000
b101101 #
1"
#450000000000
0"
#455000000000
b101110 #
1"
#460000000000
0"
#465000000000
b101111 #
1"
#470000000000
0"
#475000000000
b110000 #
1"
#480000000000
0"
#485000000000
b110001 #
1"
#490000000000
0"
#495000000000
1!
b0 #
1"
#500000000000
0"
#505000000000
b1 #
1"
#510000000000
0"
#515000000000
b10 #
1"
#520000000000
0"
#525000000000
b11 #
1"
#530000000000
0"
#535000000000
b100 #
1"
#540000000000
0"
#545000000000
b101 #
1"
#550000000000
0"
#555000000000
b110 #
1"
#560000000000
0"
#565000000000
b111 #
1"
#570000000000
0"
#575000000000
b1000 #
1"
#580000000000
0"
#585000000000
b1001 #
1"
#590000000000
0"
#595000000000
b1010 #
1"
#600000000000
0"
#605000000000
b1011 #
1"
#610000000000
0"
#615000000000
b1100 #
1"
#620000000000
0"
#625000000000
b1101 #
1"
#630000000000
0"
#635000000000
b1110 #
1"
#640000000000
0"
#645000000000
b1111 #
1"
#650000000000
0"
#655000000000
b10000 #
1"
#660000000000
0"
#665000000000
b10001 #
1"
#670000000000
0"
#675000000000
b10010 #
1"
#680000000000
0"
#685000000000
b10011 #
1"
#690000000000
0"
#695000000000
b10100 #
1"
#700000000000
0"
#705000000000
b10101 #
1"
#710000000000
0"
#715000000000
b10110 #
1"
#720000000000
0"
#725000000000
b10111 #
1"
#730000000000
0"
#735000000000
b11000 #
1"
#740000000000
0"
#745000000000
b11001 #
1"
#750000000000
0"
#755000000000
b11010 #
1"
#760000000000
0"
#765000000000
b11011 #
1"
#770000000000
0"
#775000000000
b11100 #
1"
#780000000000
0"
#785000000000
b11101 #
1"
#790000000000
0"
#795000000000
b11110 #
1"
#800000000000
0"
#805000000000
b11111 #
1"
#810000000000
0"
#815000000000
b100000 #
1"
#820000000000
0"
#825000000000
b100001 #
1"
#830000000000
0"
#835000000000
b100010 #
1"
#840000000000
0"
#845000000000
b100011 #
1"
#850000000000
0"
#855000000000
b100100 #
1"
#860000000000
0"
#865000000000
b100101 #
1"
#870000000000
0"
#875000000000
b100110 #
1"
#880000000000
0"
#885000000000
b100111 #
1"
#890000000000
0"
#895000000000
b101000 #
1"
#900000000000
0"
#905000000000
b101001 #
1"
#910000000000
0"
#915000000000
b101010 #
1"
#920000000000
0"
#925000000000
b101011 #
1"
#930000000000
0"
#935000000000
b101100 #
1"
#940000000000
0"
#945000000000
b101101 #
1"
#950000000000
0"
#955000000000
b101110 #
1"
#960000000000
0"
#965000000000
b101111 #
1"
#970000000000
0"
#975000000000
b110000 #
1"
#980000000000
0"
#985000000000
b110001 #
1"
#990000000000
0"
#995000000000
0!
b0 #
1"
#1000000000000
0"
#1005000000000
b1 #
1"
#1010000000000
0"
#1015000000000
b10 #
1"
#1020000000000
0"
#1025000000000
b11 #
1"
#1030000000000
0"
#1035000000000
b100 #
1"
#1040000000000
0"
#1045000000000
b101 #
1"
#1050000000000
0"
#1055000000000
b110 #
1"
#1060000000000
0"
#1065000000000
b111 #
1"
#1070000000000
0"
#1075000000000
b1000 #
1"
#1080000000000
0"
#1085000000000
b1001 #
1"
#1090000000000
0"
#1095000000000
b1010 #
1"
#1100000000000
0"
#1105000000000
b1011 #
1"
#1110000000000
0"
#1115000000000
b1100 #
1"
#1120000000000
0"
#1125000000000
b1101 #
1"
#1130000000000
0"
#1135000000000
b1110 #
1"
#1140000000000
0"
#1145000000000
b1111 #
1"
#1150000000000
0"
#1155000000000
b10000 #
1"
#1160000000000
0"
#1165000000000
b10001 #
1"
#1170000000000
0"
#1175000000000
b10010 #
1"
#1180000000000
0"
#1185000000000
b10011 #
1"
#1190000000000
0"
#1195000000000
b10100 #
1"
#1200000000000
0"
#1205000000000
b10101 #
1"
#1210000000000
0"
#1215000000000
b10110 #
1"
#1220000000000
0"
#1225000000000
b10111 #
1"
#1230000000000
0"
#1235000000000
b11000 #
1"
#1240000000000
0"
#1245000000000
b11001 #
1"
#1250000000000
0"
#1255000000000
b11010 #
1"
#1260000000000
0"
#1265000000000
b11011 #
1"
#1270000000000
0"
#1275000000000
b11100 #
1"
#1280000000000
0"
#1285000000000
b11101 #
1"
#1290000000000
0"
#1295000000000
b11110 #
1"
#1300000000000
0"
#1305000000000
b11111 #
1"
#1310000000000
0"
#1315000000000
b100000 #
1"
#1320000000000
0"
#1325000000000
b100001 #
1"
#1330000000000
0"
#1335000000000
b100010 #
1"
#1340000000000
0"
#1345000000000
b100011 #
1"
#1350000000000
0"
#1355000000000
b100100 #
1"
#1360000000000
0"
#1365000000000
b100101 #
1"
#1370000000000
0"
#1375000000000
b100110 #
1"
#1380000000000
0"
#1385000000000
b100111 #
1"
#1390000000000
0"
#1395000000000
b101000 #
1"
#1400000000000
0"
#1405000000000
b101001 #
1"
#1410000000000
0"
#1415000000000
b101010 #
1"
#1420000000000
0"
#1425000000000
b101011 #
1"
#1430000000000
0"
#1435000000000
b101100 #
1"
#1440000000000
0"
#1445000000000
b101101 #
1"
#1450000000000
0"
#1455000000000
b101110 #
1"
#1460000000000
0"
#1465000000000
b101111 #
1"
#1470000000000
0"
#1475000000000
b110000 #
1"
#1480000000000
0"
#1485000000000
b110001 #
1"
#1490000000000
0"
#1495000000000
1!
b0 #
1"
#1500000000000
0"
#1505000000000
b1 #
1"
#1510000000000
0"
#1515000000000
b10 #
1"
#1520000000000
0"
#1525000000000
b11 #
1"
#1530000000000
0"
#1535000000000
b100 #
1"
#1540000000000
0"
#1545000000000
b101 #
1"
#1550000000000
0"
#1555000000000
b110 #
1"
#1560000000000
0"
#1565000000000
b111 #
1"
#1570000000000
0"
#1575000000000
b1000 #
1"
#1580000000000
0"
#1585000000000
b1001 #
1"
#1590000000000
0"
#1595000000000
b1010 #
1"
#1600000000000
0"
#1605000000000
b1011 #
1"
#1610000000000
0"
#1615000000000
b1100 #
1"
#1620000000000
0"
#1625000000000
b1101 #
1"
#1630000000000
0"
#1635000000000
b1110 #
1"
#1640000000000
0"
#1645000000000
b1111 #
1"
#1650000000000
0"
#1655000000000
b10000 #
1"
#1660000000000
0"
#1665000000000
b10001 #
1"
#1670000000000
0"
#1675000000000
b10010 #
1"
#1680000000000
0"
#1685000000000
b10011 #
1"
#1690000000000
0"
#1695000000000
b10100 #
1"
#1700000000000
0"
#1705000000000
b10101 #
1"
#1710000000000
0"
#1715000000000
b10110 #
1"
#1720000000000
0"
#1725000000000
b10111 #
1"
#1730000000000
0"
#1735000000000
b11000 #
1"
#1740000000000
0"
#1745000000000
b11001 #
1"
#1750000000000
0"
#1755000000000
b11010 #
1"
#1760000000000
0"
#1765000000000
b11011 #
1"
#1770000000000
0"
#1775000000000
b11100 #
1"
#1780000000000
0"
#1785000000000
b11101 #
1"
#1790000000000
0"
#1795000000000
b11110 #
1"
#1800000000000
0"
#1805000000000
b11111 #
1"
#1810000000000
0"
#1815000000000
b100000 #
1"
#1820000000000
0"
#1825000000000
b100001 #
1"
#1830000000000
0"
#1835000000000
b100010 #
1"
#1840000000000
0"
#1845000000000
b100011 #
1"
#1850000000000
0"
#1855000000000
b100100 #
1"
#1860000000000
0"
#1865000000000
b100101 #
1"
#1870000000000
0"
#1875000000000
b100110 #
1"
#1880000000000
0"
#1885000000000
b100111 #
1"
#1890000000000
0"
#1895000000000
b101000 #
1"
#1900000000000
0"
#1905000000000
b101001 #
1"
#1910000000000
0"
#1915000000000
b101010 #
1"
#1920000000000
0"
#1925000000000
b101011 #
1"
#1930000000000
0"
#1935000000000
b101100 #
1"
#1940000000000
0"
#1945000000000
b101101 #
1"
#1950000000000
0"
#1955000000000
b101110 #
1"
#1960000000000
0"
#1965000000000
b101111 #
1"
#1970000000000
0"
#1975000000000
b110000 #
1"
#1980000000000
0"
#1985000000000
b110001 #
1"
#1990000000000
0"
#1995000000000
0!
b0 #
1"
