Hdl/timer/timer_ten.v
module timer_ten(input wire [3:0] data, input wire loadn,input wire clk,input wire clrn, input wire en,
               output reg [3:0]  out, output reg tc, output reg zero );

always @(posedge clk, posedge clrn)
    begin
        if (~en);
        else if(clrn)
        begin
            out <= 4'b0000;
            tc <= 1'b0; 
            zero <= 1'b1;
        end
        else
        begin
            if(data==4'b0000)
            begin
                out <= 4'b1001;
                tc <= 1'b1;
                zero <= 1'b0;
            end
            else if(data==4'b0001)
            begin
                out <= 4'b0000;
                tc <= 1'b0;
                zero <= 1'b1;
            end
            else
                begin
                    out <=  (data==4'b1001)? 4'b1000:
                            (data==4'b1000)? 4'b0111:
                            (data==4'b0111)? 4'b0110:
                            (data==4'b0110)? 4'b0101:
                            (data==4'b0101)? 4'b0100:
                            (data==4'b0100)? 4'b0011:
                            (data==4'b0011)? 4'b0010:4'b0001;
                    tc <= 1'b0;
                    zero <= 1'b0;
                     
                end
        end
    end

endmodule

Tests/Timer/timer_ten_tb.v
`timescale 1ms/1ps

module timer_ten_tb();

reg clk=1;
reg loadn=1;
reg clrn=1;
reg en=0;
reg [3:0] in;
wire [3:0] out;
wire tc;
wire zero;

timer_ten DUT(in,loadn,clk,clrn,en,out,tc,zero);


always
begin
    #10 clk = ~clk;    
end

always @(posedge clk && loadn==1)
begin
    $display("out = %d || tc = %d || zero = %d", out,tc,zero);    
end    

initial 
    begin
        in = 9;
        while(in>=0)
        begin
        if(in==0) $finish;
        $display("TESTE IN = %d", in);
        loadn = 0;
        en = 1;
        in <= in - 1;
        #20 loadn = 1;
        #(10*10*2);
        end

    end
endmodule

wave/timer_ten.vcd
$date
	Thu Apr 29 12:03:53 2021
$end
$version
	Icarus Verilog
$end
$timescale
	1ps
$end
$scope module timer_ten_tb $end
$var wire 1 ! zero $end
$var wire 1 " tc $end
$var wire 4 # out [3:0] $end
$var reg 1 $ clk $end
$var reg 1 % clrn $end
$var reg 1 & en $end
$var reg 4 ' in [3:0] $end
$var reg 1 ( loadn $end
$scope module DUT $end
$var wire 1 $ clk $end
$var wire 1 % clrn $end
$var wire 4 ) data [3:0] $end
$var wire 1 & en $end
$var wire 1 ( loadn $end
$var wire 1 " tc $end
$var reg 4 * out [3:0] $end
$var reg 1 ! zero $end
$upscope $end
$upscope $end
$enddefinitions $end
#0
$dumpvars
b1000 *
b1000 )
0(
b1000 '
1&
1%
1$
b1000 #
0"
0!
$end
#5000000000
0$
#10000000000
0"
b111 #
b111 *
1$
1(
#15000000000
0$
#20000000000
b110 #
b110 *
1$
#25000000000
0$
#30000000000
b101 #
b101 *
1$
#35000000000
0$
#40000000000
b100 #
b100 *
1$
#45000000000
0$
#50000000000
0"
b11 #
b11 *
1$
#55000000000
0$
#60000000000
b10 #
b10 *
1$
#65000000000
0$
#70000000000
0"
b1 #
b1 *
1$
#75000000000
0$
#80000000000
1"
1!
b0 #
b0 *
1$
#85000000000
0$
#90000000000
0"
0!
b1001 #
b1001 *
1$
#95000000000
0$
#100000000000
b1000 #
b1000 *
1$
